text2mem_adapters/__init__.py
text2mem_adapters-0.1.0.dist-info/METADATA
text2mem_adapters-0.1.0.dist-info/WHEEL
text2mem_adapters-0.1.0.dist-info/top_level.txt
text2mem_adapters-0.1.0.dist-info/RECORD
