Metadata-Version: 2.4
Name: text2mem-adapters
Version: 0.1.0
Summary: Adapters for text2mem
Home-page: https://github.com/yourusername/text2mem-adapters
Author: Your Name
Author-email: your.email@example.com
Classifier: Programming Language :: Python :: 3
Classifier: License :: OSI Approved :: MIT License
Classifier: Operating System :: OS Independent
Requires-Python: >=3.6
Dynamic: author
Dynamic: author-email
Dynamic: classifier
Dynamic: description
Dynamic: description-content-type
Dynamic: home-page
Dynamic: requires-python
Dynamic: summary
